__init__.py
hello.py
duna-0.0.0.dist-info/METADATA
duna-0.0.0.dist-info/WHEEL
duna-0.0.0.dist-info/top_level.txt
duna-0.0.0.dist-info/RECORD
